{"listaPedidos":[{"clientePedido":{"nome":"Lenon","endereco":"Casa A"},"produtoPedido":[{"produto":{"nomeProduto":"batata","preco":10.0,"descricaoProduto":"null"},"quantidade":2"precoTotal":20.0}, {"produto":{"nomeProduto":"Khal","preco":15.0,"descricaoProduto":"null"},"quantidade":2"precoTotal":30.0}],"horarioPedido":"21-outubro-2020 0:29:30","precoFinal":50.0}]}{"listaPedidos":[{"clientePedido":{"nome":"Lenon","endereco":"Casa A"},"produtoPedido":[{"produto":{"nomeProduto":"batata","preco":10.0,"descricaoProduto":"null"},"quantidade":2"precoTotal":20.0}, {"produto":{"nomeProduto":"Khal","preco":15.0,"descricaoProduto":"null"},"quantidade":2"precoTotal":30.0}],"horarioPedido":"21-outubro-2020 4:54:5","precoFinal":50.0}]}